nonebot_plugin_exchangerate/__init__.py
nonebot_plugin_exchangerate/config.py
nonebot_plugin_exchangerate/exchangerate.py
nonebot_plugin_exchangerate-0.1.2.dist-info/WHEEL
nonebot_plugin_exchangerate-0.1.2.dist-info/METADATA
nonebot_plugin_exchangerate-0.1.2.dist-info/licenses/LICENSE
nonebot_plugin_exchangerate-0.1.2.dist-info/RECORD
