Metadata-Version: 2.1
Name: nonebot-plugin-exchangerate
Version: 0.1.2
Summary: NoneBot2 plugin for currency converter
License: MIT
Author-email: Akirami <Akiramiaya@outlook.com>
Requires-Python: >=3.8
Project-URL: Homepage, https://github.com/A-kirami/nonebot-plugin-exchangerate
Project-URL: Repository, https://github.com/A-kirami/nonebot-plugin-exchangerate
